rainiee_rest_client/__init__.py
rainiee_rest_client/rest_client.py
rainiee_rest_client/base/__init__.py
rainiee_rest_client/base/client.py
rainiee_rest_client/base/login.py
rainiee_rest_client-1.0.3.dist-info/METADATA
rainiee_rest_client-1.0.3.dist-info/WHEEL
rainiee_rest_client-1.0.3.dist-info/top_level.txt
rainiee_rest_client-1.0.3.dist-info/RECORD
