Metadata-Version: 2.1
Name: rainiee-rest-client
Version: 1.0.3
Summary: rainiee rest api client
Home-page: https://github.com/Rainiee-Technology
Author: rainiee
Author-email: rainiee@163.com
License: MIT
Platform: UNKNOWN
Requires-Python: >=3
